{
  "partitionDeps": [
    {
      "in": "requete_pro",
      "out": "TBC_WEB_CLIC_DETAIL",
      "idim": "day",
      "odim": "day",
      "func": "equals",
      "params": {}
    },
    {
      "in": "PDM_event",
      "out": "TBC_WEB_CLIC_DETAIL",
      "idim": "day",
      "odim": "day",
      "func": "equals",
      "params": {}
    }
  ],
  "inputs": [
    "requete_pro",
    "PDM_event"
  ],
  "outputs": [
    "TBC_WEB_CLIC_DETAIL"
  ],
  "neverRecomputeExistingPartitions": false,
  "type": "pig",
  "params": {},
  "updateUser": "admin",
  "tags": []
}